<?xml version="1.0" encoding="UTF-8"?>
<!--
To change this license header, choose License Headers in Project Properties.
To change this template file, choose Tools | Templates
and open the template in the editor.
-->
<!DOCTYPE tiles-definitions PUBLIC "-//Apache
Software Foundation//DTD Tiles Configuration 3.0//EN"
"http://tiles.apache.org/dtds/tiles-config_3_0.dtd">

<tiles-definitions>
    <definition name="baseLayout" template="/WEB-INF/layout/base.jsp">
        <put-attribute name="title" value="Trang chu" />
        <put-attribute name="header" value="/WEB-INF/layout/header.jsp" />
        <put-attribute name="footer" value="/WEB-INF/layout/footer.jsp" />
        <put-attribute name="content" value="base" />
    </definition>
    
    <definition name="index" extends="baseLayout">
        <put-attribute name="title" value="Trang chu"/>
        <put-attribute name="content" value="/WEB-INF/jsp/index.jsp" />
        
    </definition>
    
    <definition name="hello" extends="baseLayout">
        <put-attribute name="title" value="Hello" />
        <put-attribute name="content" value="/WEB-INF/jsp/departments.jsp" />
        
    </definition>
    
    <definition name="departments" extends="baseLayout">
        <put-attribute name="title" value="Departments" />
        <put-attribute name="content" value="/WEB-INF/jsp/departments.jsp" />
        
    </definition>
    
    <definition name="about" extends="baseLayout">
        <put-attribute name="title" value="About" />
        <put-attribute name="content" value="/WEB-INF/jsp/about.jsp" />
        
    </definition>
    
    <definition name="contact" extends="baseLayout">
        <put-attribute name="title" value="Contact" />
        <put-attribute name="content" value="/WEB-INF/jsp/contact.jsp" />
        
    </definition>
    
    
    
    <definition name="login1" template="/WEB-INF/jsp/login.jsp"></definition>
    <definition name="register" template="/WEB-INF/jsp/register.jsp"></definition>
    <definition name="register1" template="/WEB-INF/jsp/register1.jsp"></definition>
    
    <definition name="adminView" extends="baseLayout">
        <put-attribute name="title" value="Admin" />
        <put-attribute name="header" value="/WEB-INF/jsp/administrator/adminView.jsp" />
        
    </definition>
    
    <definition name="listDoctor" extends="baseLayout">
        <put-attribute name="title" value="listDoctor" />
        <put-attribute name="header" value="/WEB-INF/jsp/administrator/adminView.jsp" />
        <put-attribute name="content" value="/WEB-INF/jsp/administrator/listDoctor.jsp" />
        
    </definition>
    <definition name="addDoctor" template="/WEB-INF/jsp/administrator/addDoctor.jsp">     
    </definition>
    
    <definition name="list-customers" extends="baseLayout">
        <put-attribute name="title" value="ListDocotr"/>
        <put-attribute name="header" value="/WEB-INF/jsp/administrator/adminView.jsp" />
        <put-attribute name="content" value="/WEB-INF/jsp/administrator/list-customer.jsp"/>
    </definition>  
    
    <definition name="editEmployee" template="/WEB-INF/jsp/administrator/editEmployee.jsp"></definition>
    <definition name="editphanca" template="/WEB-INF/jsp/administrator/editphanca.jsp"></definition>
    
    <definition name="phanca" template="/WEB-INF/jsp/administrator/phanca.jsp"></definition>
    <definition name="phancadoctor" template="/WEB-INF/jsp/doctor/phanca.jsp"></definition>
    <definition name="phancanurse" template="/WEB-INF/jsp/nurse/phanca.jsp"></definition>
    
    <definition name="list-medicine" extends="baseLayout">  
        <put-attribute name="title" value="ListMedicine"/>
        <put-attribute name="header" value="/WEB-INF/jsp/administrator/adminView.jsp" />
        <put-attribute name="content" value="/WEB-INF/jsp/administrator/list-medicine.jsp"/>
    </definition>
    
    <definition name="medicine-form" template="/WEB-INF/jsp/administrator/medicine.jsp">
    </definition>
    
    <definition name="updateinformation" extends="baseLayout">
        <put-attribute name="title" value="Information"/>
        <put-attribute name="content" value="/WEB-INF/jsp/updateinformation.jsp"/>
    </definition>
    <!-- Doctor -->
    <definition name="doctorview" extends="baseLayout">
        <put-attribute name="title" value="doctor" />
        <put-attribute name="header" value="/WEB-INF/jsp/doctor/doctorview.jsp" />
        
    </definition>
    
    
    <definition name="list-patient" extends="baseLayout">
        <put-attribute name="title" value="Listpatient"/>
        <put-attribute name="header" value="/WEB-INF/jsp/doctor/doctorview.jsp" />
        <put-attribute name="content" value="/WEB-INF/jsp/doctor/list-patient.jsp"/>
    </definition>
    
    <definition name="editForm" template="/WEB-INF/jsp/editInformationForm.jsp">
    </definition>
    <definition name="changepasswork" template="/WEB-INF/jsp/changepasswork.jsp">
    </definition>
    
    
    
    <definition name="nurseView" extends="baseLayout">
        <put-attribute name="title" value="Nurse" />
        <put-attribute name="header" value="/WEB-INF/jsp/nurse/nurseView.jsp" />        
    </definition>
    
    <definition name="patient" extends="baseLayout">  
        <put-attribute name="title" value="Patient"/>
        <put-attribute name="header" value="/WEB-INF/jsp/nurse/nurseView.jsp" />
        <put-attribute name="content" value="/WEB-INF/jsp/nurse/patient-list.jsp"/>
    </definition>
    <definition name="patient-list" extends="baseLayout">  
        <put-attribute name="title" value="Patient"/>
        <put-attribute name="header" value="/WEB-INF/jsp/nurse/nurseView.jsp" />
        <put-attribute name="content" value="/WEB-INF/jsp/doctor/patient-list.jsp"/>
    </definition>
    <definition name="benhan" extends="baseLayout">  
        <put-attribute name="title" value="Benhan"/>
        <put-attribute name="header" value="/WEB-INF/jsp/nurse/nurseView.jsp" />
        <put-attribute name="content" value="/WEB-INF/jsp/doctor/benhan.jsp"/>
    </definition>
    
    <definition name="informationPatient" template="/WEB-INF/jsp/nurse/informationPatient.jsp">
    </definition>
    <definition name="dkkham" template="/WEB-INF/jsp/dkkham.jsp"></definition>
    <definition name="addbenhan" template="/WEB-INF/jsp/doctor/addbenhan.jsp"></definition>
    <definition name="apoitment" template="/WEB-INF/jsp/apoitment.jsp">    
    </definition>
    
    <definition name="kedon" extends="baseLayout">
        <put-attribute name="title" value="Ke Don" />
        <put-attribute name="content" value="/WEB-INF/jsp/doctor/kedon.jsp" />
    </definition>
    
    <definition name="chitiet" extends="baseLayout">
        <put-attribute name="title" value="Chi tiet don thuoc" />
        <put-attribute name="content" value="/WEB-INF/jsp/doctor/chitiet.jsp" />
    </definition>
    
</tiles-definitions>
